{
    "enemies": {
        "enemy_01_red": {
            "sprite_name": "alien1_red",
            "color": "Red",
            "health": 30,
            "radius": 40,
            "weapon_name": "enemy_weapon"
        },
        "enemy_01_blue": {
            "sprite_name": "alien1_blue",
            "color": "Blue",
            "health": 30,
            "radius": 40,
            "weapon_name": "enemy_weapon"
        },
        "enemy_02_red": {
            "sprite_name": "alien25_red",
            "color": "Red",
            "health": 30,
            "radius": 40,
            "weapon_name": "enemy_weapon"
        },
        "enemy_02_blue": {
            "sprite_name": "alien25_blue",
            "color": "Blue",
            "health": 30,
            "radius": 40,
            "weapon_name": "enemy_weapon"
        }
    }
}
